{
  "vocabulary": {
    "beginner": {
      "section1": {
        "sectionDescription": "greetings",
        "questions": [
          {
            "questionType": "mcq",
            "question": "Which one of these is 'hello'?",
            "word": "salut",
            "options": ["bonjour", "oui", "merci", "salut"],
            "answer": "salut"
          },
          {
            "questionType": "fill-in",
            "question": "Say 'Good morining' to Rhoda. __ Rhoda!",
            "word": "bonjour",
            "options": ["bonjour", "oui", "salut", "merci"],
            "answer": "bonjour"
          },

          {
            "questionType": "mcq",
            "question": "Which one of these is 'goodbye'?",
            "word": "au revoir",
            "options": ["merci", "oui", "au revoir", "salut"],
            "answer": "au revoir"
          },

          {
            "questionType": "mcq",
            "question": "Select the correct meaning: 'goodnight'?",
            "word": "bonne nuit",
            "options": ["merci", "oui", "au revoir", "bonne nuit"],
            "answer": "bonne nuit"
          },
          {
            "questionType": "mcq",
            "question": "What do you hear?",
            "word": "bonsoir",
            "options": ["merci", "bonsoir", "au revoir", "salut"],
            "answer": "bonsoir"
          }
        ]
      },
     "section2": {
        "sectionDescription": "everydayWords",
        "questions": [
          {
            "questionType": "mcq",
            "question": "yes",
            "word": "oui",
            "options": ["oui", "nuit", "fille", "je"],
            "answer": "oui"
          },
          {
            "questionType": "fill-in",
            "question": "__ suis Sam!",
            "word": "je",
            "options": ["tu", "nous", "vous", "ils"],
            "answer": "je"
          },

          {
            "questionType": "mcq",
            "question": "is",
            "word": "suis",
            "options": ["nous", "suis", "vous", "les"],
            "answer": "suis"
          },

          {
            "questionType": "mcq",
            "question": "Select the correct meaning: 'no'?",
            "word": "non",
            "options": ["oui", "non", "moi", "jour"],
            "answer": "non"
          },

          {
            "questionType": "mcq",
            "question": "Which of these is 'maybe'",
            "word": "peut-être",
            "options": ["oui", "non", "moi", "peut-être"],
            "answer": "peut-être"
          }
        ]
      }
    },
    "intermediate": {
     "section1": {
        "sectionDescription": "greetings",
        "questions": [
          {
            "questionType": "mcq",
            "question": "Which one of these is 'thank you'?",
            "word": "merci",
            "options": ["bonjour", "oui", "merci", "salut"],
            "answer": "merci"
          },
          {
            "questionType": "fill-in",
            "question": "Please: 'S'il vous ___",
            "word": "plaît",
            "options": ["rein", "plait", "oui", "non"],
            "answer": "plaît"
          },

          {
            "questionType": "mcq",
            "question": "Which one of these is 'nice to meet you'?",
            "word": "enchanté(e)",
            "options": ["merci", "oui", "enchantée", "plait"],
            "answer": "enchanté(e)"
          },

          {
            "questionType": "mcq",
            "question": "Select the correct meaning: 'welcome'?",
            "word": "bienvenue",
            "options": ["merci", "oui", "enchantée", "bienvenue"],
            "answer": "bienvenue"
          },
          {
            "questionType": "mcq",
            "question": "good day",
            "word": "bonne journée",
            "options": ["merci", "bonne journée", "bienvenue", "salut"],
            "answer": "bonne journée"
          }
        ]
      },
     "section2": {
        "sectionDescription": "everydayWords",
        "questions": [
          {
            "questionType": "mcq",
            "question": "The day",
            "word": "le jour",
            "options": ["le jour", "la nuit", "une fille", "je"],
            "answer": "le jour"
          },
          {
            "questionType": "fill-in",
            "question": "__ suis Sam!",
            "word": "je",
            "options": ["tu", "nous", "vous", "ils"],
            "answer": "je"
          },

          {
            "questionType": "mcq",
            "question": "Which of these is 'house'",
            "word": "maison",
            "options": ["jour", "maison", "livre", "école"],
            "answer": "maison"
          },

          {
            "questionType": "mcq",
            "question": "Select the correct meaning: 'work'?",
            "word": "travail",
            "options": ["maison", "livre", "travail", "jour"],
            "answer": "travail"
          },

          {
            "questionType": "mcq",
            "question": "Which of these is 'store'",
            "word": "magasin",
            "options": ["magasin", "maison", "livre", "école"],
            "answer": "magasin"
          }
        ]
      }
    },
    "advanced": {
      "greetings": [
        {
          "questionType": "mcq",
          "question": "Which one of these is 'hello'?",
          "word": "salut",
          "options": ["bonjour", "oui", "merci", "salut"],
          "answer": "salut"
        },
        {
          "questionType": "fill-in",
          "question": "__ Rhoda!",
          "word": "salut",
          "options": ["bonjour", "oui", "salut", "merci"],
          "answer": "salut"
        }
      ],
      "everydayWords": [
        {
          "questionType": "mcq",
          "question": "Which one of these is 'hello'?",
          "word": "salut",
          "options": ["bonjour", "oui", "merci", "salut"],
          "answer": "salut"
        },
        {
          "questionType": "fill-in",
          "question": "__ Rhoda!",
          "word": "salut",
          "options": ["bonjour", "oui", "salut", "merci"],
          "answer": "salut"
        }
      ]
    }
  },
  "sentenceBuilding": {
    "greetings": [
      {
        "questionType": "mcq",
        "question": "Which one of these is 'hello'?",
        "word": "salut",
        "options": ["bonjour", "oui", "merci", "salut"],
        "answer": "salut"
      },
      {
        "questionType": "fill-in",
        "question": "__ Rhoda!",
        "word": "salut",
        "options": ["bonjour", "oui", "salut", "merci"],
        "answer": "salut"
      }
    ],
    "everydayWords": [
      {
        "questionType": "mcq",
        "question": "Which one of these is 'hello'?",
        "word": "salut",
        "options": ["bonjour", "oui", "merci", "salut"],
        "answer": "salut"
      },
      {
        "questionType": "fill-in",
        "question": "__ Rhoda!",
        "word": "salut",
        "options": ["bonjour", "oui", "salut", "merci"],
        "answer": "salut"
      }
    ]
  },
  "dialogueSimulation": {
    "greetings": [
      {
        "questionType": "mcq",
        "question": "Which one of these is 'hello'?",
        "word": "salut",
        "options": ["bonjour", "oui", "merci", "salut"],
        "answer": "salut"
      },
      {
        "questionType": "fill-in",
        "question": "__ Rhoda!",
        "word": "salut",
        "options": ["bonjour", "oui", "salut", "merci"],
        "answer": "salut"
      }
    ],
    "everydayWords": [
      {
        "questionType": "mcq",
        "question": "Which one of these is 'hello'?",
        "word": "salut",
        "options": ["bonjour", "oui", "merci", "salut"],
        "answer": "salut"
      },
      {
        "questionType": "fill-in",
        "question": "__ Rhoda!",
        "word": "salut",
        "options": ["bonjour", "oui", "salut", "merci"],
        "answer": "salut"
      }
    ]
  }
}
